aws_ec2_provisioner/__init__.py
aws_ec2_provisioner/autoscaling.py
aws_ec2_provisioner/conf.py
aws_ec2_provisioner/errors.py
aws_ec2_provisioner/load_balancer.py
aws_ec2_provisioner/main.py
aws_ec2_provisioner/menu.py
aws_ec2_provisioner/security_groups.py
aws_ec2_provisioner/utils.py
aws_ec2_provisioner/vpc.py
aws_ec2_provisioner-0.1.1.dist-info/LICENSE
aws_ec2_provisioner-0.1.1.dist-info/METADATA
aws_ec2_provisioner-0.1.1.dist-info/WHEEL
aws_ec2_provisioner-0.1.1.dist-info/entry_points.txt
aws_ec2_provisioner-0.1.1.dist-info/top_level.txt
aws_ec2_provisioner-0.1.1.dist-info/RECORD
