Metadata-Version: 2.1
Name: aws-ec2-provisioner
Version: 0.1.1
Summary: POC boto3 resource provisioner
Home-page: https://github.com/valeramaniuk/aws-ec2-provisioner
Author: Valera Maniuk
Author-email: valeramaniuk@protonmail.com
License: UNKNOWN
Platform: UNKNOWN
Requires-Dist: click
Requires-Dist: boto3
Requires-Dist: pprint
